django_electric/__init__.py
django_electric/apps.py
django_electric/client.py
django_electric/conf.py
django_electric/decorators.py
django_electric/exceptions.py
django_electric/managers.py
django_electric/middleware.py
django_electric/models.py
django_electric/signals.py
django_electric/sync.py
django_electric/management/__init__.py
django_electric/management/commands/__init__.py
django_electric/management/commands/electric_status.py
django_electric/management/commands/electric_sync.py
django_electric-0.1.1.dist-info/licenses/LICENSE
django_electric-0.1.1.dist-info/METADATA
django_electric-0.1.1.dist-info/WHEEL
django_electric-0.1.1.dist-info/top_level.txt
django_electric-0.1.1.dist-info/RECORD
