Metadata-Version: 2.4
Name: django-electric
Version: 0.1.1
Summary: Django integration for Electric SQL real-time sync engine
Author-email: Your Name <your.email@example.com>
License-Expression: Apache-2.0
Project-URL: Homepage, https://github.com/Apoorvgarg-Creator/dj-electric
Project-URL: Documentation, https://github.com/Apoorvgarg-Creator/dj-electric/wiki
Project-URL: Repository, https://github.com/Apoorvgarg-Creator/dj-electric
Project-URL: Issues, https://github.com/Apoorvgarg-Creator/dj-electric/issues
Keywords: django,electric-sql,sync,real-time,offline-first,local-first
Classifier: Development Status :: 3 - Alpha
Classifier: Intended Audience :: Developers
Classifier: Programming Language :: Python :: 3
Classifier: Programming Language :: Python :: 3.9
Classifier: Programming Language :: Python :: 3.10
Classifier: Programming Language :: Python :: 3.11
Classifier: Programming Language :: Python :: 3.12
Classifier: Framework :: Django
Classifier: Framework :: Django :: 4.2
Classifier: Framework :: Django :: 5.0
Classifier: Topic :: Database
Classifier: Topic :: Internet :: WWW/HTTP
Requires-Python: >=3.9
License-File: LICENSE
Requires-Dist: Django>=4.2
Requires-Dist: requests>=2.31.0
Requires-Dist: websockets>=12.0
Requires-Dist: python-dateutil>=2.8.2
Provides-Extra: dev
Requires-Dist: pytest>=7.4.0; extra == "dev"
Requires-Dist: pytest-django>=4.5.0; extra == "dev"
Requires-Dist: pytest-cov>=4.1.0; extra == "dev"
Requires-Dist: pytest-asyncio>=0.21.0; extra == "dev"
Requires-Dist: black>=23.0.0; extra == "dev"
Requires-Dist: isort>=5.12.0; extra == "dev"
Requires-Dist: flake8>=6.0.0; extra == "dev"
Requires-Dist: mypy>=1.5.0; extra == "dev"
Requires-Dist: django-stubs>=4.2.0; extra == "dev"
Dynamic: license-file
